{
  "audiovisual_files": {
    "aa63ba65-6553-4364-bf31-64a42e90aa1e": {
      "label": "AV File 2",
      "duration": 0
    }
  },
  "auto_generate_web_page": true,
  "description": [
    {
      "type": "paragraph",
      "children": [
        {
          "text": ""
        }
      ]
    }
  ],
  "created_at": "2025-10-27T21:19:26.429Z",
  "created_by": "tanyaclement",
  "item_type": "Audio",
  "label": "Imported Event 2",
  "updated_at": "2025-10-27T21:19:26.429Z",
  "updated_by": "tanyaclement"
}